word_counter/__init__.py
word_counter/cli.py
word_counter/counter.py
word_counter_vvvrtr-0.1.dist-info/licenses/LICENSE
word_counter_vvvrtr-0.1.dist-info/METADATA
word_counter_vvvrtr-0.1.dist-info/WHEEL
word_counter_vvvrtr-0.1.dist-info/entry_points.txt
word_counter_vvvrtr-0.1.dist-info/top_level.txt
word_counter_vvvrtr-0.1.dist-info/RECORD
