Metadata-Version: 2.4
Name: word_counter_vvvrtr
Version: 0.1
Summary: Пакет для подсчёта слов и символов в тексте
Home-page: https://github.com/vvtteu/word_counter
Author: vvvrtr
License: MIT
Classifier: Programming Language :: Python :: 3
Classifier: License :: OSI Approved :: MIT License
Requires-Python: >=3.6
License-File: LICENSE
Dynamic: author
Dynamic: classifier
Dynamic: description-content-type
Dynamic: home-page
Dynamic: license
Dynamic: license-file
Dynamic: requires-python
Dynamic: summary
